sputility/__init__.py
sputility/sputility.py
sputility/obj/__init__.py
sputility/obj/attributes.py
sputility/obj/deserialize.py
sputility/obj/enums.py
sputility/obj/primitives.py
sputility/obj/types.py
sputility/pkg/__init__.py
sputility/pkg/decompress.py
sputility/pkg/types.py
sputility-0.0.6.dist-info/licenses/LICENSE
sputility-0.0.6.dist-info/METADATA
sputility-0.0.6.dist-info/WHEEL
sputility-0.0.6.dist-info/top_level.txt
sputility-0.0.6.dist-info/RECORD
