Metadata-Version: 2.4
Name: sputility
Version: 0.0.6
Summary: System Platform Utility
Author-email: aawilliams85 <adair.williams85@gmail.com>
License: MIT License
Project-URL: Repository, https://github.com/aawilliams85/sputility.git
License-File: LICENSE
Dynamic: license-file
